moat/kv/__init__.py
moat/kv/_cfg.yaml
moat/kv/_main.py
moat/kv/client.py
moat/kv/code.py
moat/kv/config.py
moat/kv/data.py
moat/kv/errors.py
moat/kv/exceptions.py
moat/kv/model.py
moat/kv/runner.py
moat/kv/server.py
moat/kv/types.py
moat/kv/actor/__init__.py
moat/kv/actor/deletor.py
moat/kv/auth/__init__.py
moat/kv/auth/_test.py
moat/kv/auth/password.py
moat/kv/auth/root.py
moat/kv/backend/__init__.py
moat/kv/backend/mqtt.py
moat/kv/command/__init__.py
moat/kv/command/acl.py
moat/kv/command/auth.py
moat/kv/command/code.py
moat/kv/command/codec.py
moat/kv/command/data.py
moat/kv/command/error.py
moat/kv/command/internal.py
moat/kv/command/job.py
moat/kv/command/log.py
moat/kv/command/server.py
moat/kv/command/type.py
moat/kv/command/dump/__init__.py
moat/kv/mock/__init__.py
moat/kv/mock/mqtt.py
moat/kv/mock/tracer.py
moat/kv/obj/__init__.py
moat/kv/obj/command.py
moat_kv-0.71.24.dist-info/licenses/LICENSE
moat_kv-0.71.24.dist-info/licenses/LICENSE.APACHE2
moat_kv-0.71.24.dist-info/licenses/LICENSE.MIT
moat_kv-0.71.24.dist-info/licenses/LICENSE.txt
moat_kv-0.71.24.dist-info/METADATA
moat_kv-0.71.24.dist-info/WHEEL
moat_kv-0.71.24.dist-info/top_level.txt
moat_kv-0.71.24.dist-info/RECORD
