Metadata-Version: 2.4
Name: moat-kv
Version: 0.71.24
Summary: A distributed no-master key-value store
Author-email: Matthias Urlichs <matthias@urlichs.de>
Project-URL: homepage, https://m-o-a-t.org
Project-URL: repository, https://github.com/M-o-a-T/moat
Keywords: MoaT
Classifier: Development Status :: 4 - Beta
Classifier: Intended Audience :: Information Technology
Classifier: Framework :: AsyncIO
Classifier: Framework :: Trio
Classifier: Operating System :: POSIX :: Linux
Classifier: Operating System :: MacOS :: MacOS X
Classifier: Operating System :: Microsoft :: Windows
Classifier: Programming Language :: Python :: 3
Classifier: Topic :: Database
Classifier: Topic :: Home Automation
Classifier: Topic :: System :: Distributed Computing
Requires-Python: >=3.8
License-File: LICENSE
License-File: LICENSE.APACHE2
License-File: LICENSE.MIT
License-File: LICENSE.txt
Requires-Dist: asyncclick>7.99
Requires-Dist: trio>=0.22
Requires-Dist: anyio>=4
Requires-Dist: range_set>=0.2
Requires-Dist: attrs>=22
Requires-Dist: asyncactor~=0.27.0
Requires-Dist: asyncscope>=0.10.4
Requires-Dist: jsonschema>=2.5
Requires-Dist: ruyaml>=0.89
Requires-Dist: PyNaCl>=1.3
Requires-Dist: moat-lib-diffiehellman~=0.13.5
Requires-Dist: moat-link~=0.2.35
Requires-Dist: psutil
Requires-Dist: simpleeval>=0.9.10
Requires-Dist: moat-mqtt~=0.42.12
Requires-Dist: moat-util~=0.61.1
Requires-Dist: exceptiongroup; python_version < "3.11"
Requires-Dist: moat-lib-codec~=0.4.9
Requires-Dist: moat-lib-config~=0.1.0
Requires-Dist: moat-lib-run~=0.1.0
Dynamic: license-file
